yamama-0.7.2.data/purelib/yamama/agents/__init__.py
yamama-0.7.2.data/purelib/yamama/agents/_exceptions.py
yamama-0.7.2.data/purelib/yamama/agents/inference_runner.py
yamama-0.7.2.data/purelib/yamama/agents/job.py
yamama-0.7.2.data/purelib/yamama/agents/jupyter.py
yamama-0.7.2.data/purelib/yamama/agents/log.py
yamama-0.7.2.data/purelib/yamama/agents/plugin.py
yamama-0.7.2.data/purelib/yamama/agents/py.typed
yamama-0.7.2.data/purelib/yamama/agents/types.py
yamama-0.7.2.data/purelib/yamama/agents/vad.py
yamama-0.7.2.data/purelib/yamama/agents/version.py
yamama-0.7.2.data/purelib/yamama/agents/worker.py
yamama-0.7.2.data/purelib/yamama/agents/beta/__init__.py
yamama-0.7.2.data/purelib/yamama/agents/beta/tools/__init__.py
yamama-0.7.2.data/purelib/yamama/agents/beta/tools/end_call.py
yamama-0.7.2.data/purelib/yamama/agents/beta/tools/send_dtmf.py
yamama-0.7.2.data/purelib/yamama/agents/beta/workflows/__init__.py
yamama-0.7.2.data/purelib/yamama/agents/beta/workflows/address.py
yamama-0.7.2.data/purelib/yamama/agents/beta/workflows/dtmf_inputs.py
yamama-0.7.2.data/purelib/yamama/agents/beta/workflows/email_address.py
yamama-0.7.2.data/purelib/yamama/agents/beta/workflows/task_group.py
yamama-0.7.2.data/purelib/yamama/agents/beta/workflows/utils.py
yamama-0.7.2.data/purelib/yamama/agents/beta/workflows/warm_transfer.py
yamama-0.7.2.data/purelib/yamama/agents/cli/__init__.py
yamama-0.7.2.data/purelib/yamama/agents/cli/cli.py
yamama-0.7.2.data/purelib/yamama/agents/cli/discover.py
yamama-0.7.2.data/purelib/yamama/agents/cli/log.py
yamama-0.7.2.data/purelib/yamama/agents/cli/proto.py
yamama-0.7.2.data/purelib/yamama/agents/cli/readchar.py
yamama-0.7.2.data/purelib/yamama/agents/cli/watcher.py
yamama-0.7.2.data/purelib/yamama/agents/inference/__init__.py
yamama-0.7.2.data/purelib/yamama/agents/inference/_utils.py
yamama-0.7.2.data/purelib/yamama/agents/inference/llm.py
yamama-0.7.2.data/purelib/yamama/agents/inference/stt.py
yamama-0.7.2.dist-info/METADATA
yamama-0.7.2.dist-info/WHEEL
yamama-0.7.2.dist-info/top_level.txt
yamama-0.7.2.dist-info/RECORD
